poetry_demo/__init__.py
poetry_demo/poetry_demo.py
poetry_demo_jcc_v1-0.1.2.dist-info/METADATA
poetry_demo_jcc_v1-0.1.2.dist-info/WHEEL
poetry_demo_jcc_v1-0.1.2.dist-info/RECORD
